README.md
setup.py
mce/__init__.py
mce/__main__.py
mce/bus.py
mce/dstest_rtsp.py
mce/jetdetect.py
mce/lucifer.py
mce/osd.py
mce/pie.conf
mce/pipeline.py
mce.egg-info/PKG-INFO
mce.egg-info/SOURCES.txt
mce.egg-info/dependency_links.txt
mce.egg-info/entry_points.txt
mce.egg-info/top_level.txt