Metadata-Version: 2.1
Name: mce
Version: 0.1.2
Summary: Mechanical Compound Eye
Home-page: UNKNOWN
Author: Michael de Gans
Author-email: michael.john.degans@gmail.com
License: UNKNOWN
Project-URL: Bug Reports, https://github.com/mdegans/mce/issues
Project-URL: Source, https://github.com/mdegans/mce/
Platform: UNKNOWN
Classifier: Development Status :: 3 - Alpha
Classifier: Intended Audience :: Developers
Classifier: Programming Language :: Python :: 3
Classifier: Programming Language :: Python :: 3.6
Classifier: Programming Language :: Python :: 3.7
Classifier: Programming Language :: Python :: 3.8
Requires-Python: >=3.6
